CHANGES.txt
MANIFEST.in
README.txt
pytest_bugzilla.py
setup.py
pytest_bugzilla.egg-info/PKG-INFO
pytest_bugzilla.egg-info/SOURCES.txt
pytest_bugzilla.egg-info/dependency_links.txt
pytest_bugzilla.egg-info/entry_points.txt
pytest_bugzilla.egg-info/not-zip-safe
pytest_bugzilla.egg-info/requires.txt
pytest_bugzilla.egg-info/top_level.txt