Metadata-Version: 1.0
Name: pytest-bugzilla
Version: 0.2
Summary: py.test bugzilla integration plugin
Home-page: http://github.com/nibrahim/pytest_bugzilla
Author: Noufal Ibrahim
Author-email: noufal@nibrahim.net.in
License: GPL
Platform: linux
Platform: osx
Platform: win32
Classifier: Development Status :: 4 - Beta
Classifier: Intended Audience :: Developers
Classifier: License :: OSI Approved :: GNU General Public License (GPL)
Classifier: Operating System :: POSIX
Classifier: Operating System :: Microsoft :: Windows
Classifier: Operating System :: MacOS :: MacOS X
Classifier: Topic :: Software Development :: Testing
Classifier: Topic :: Software Development :: Quality Assurance
Classifier: Topic :: Utilities
Classifier: Programming Language :: Python
